ipyext/__init__.py
ipyext/_version.py
ipyext/inactive.py
ipyext/writeandexecute.py
ipyext-0.1.0.dist-info/DESCRIPTION.rst
ipyext-0.1.0.dist-info/METADATA
ipyext-0.1.0.dist-info/RECORD
ipyext-0.1.0.dist-info/WHEEL
ipyext-0.1.0.dist-info/metadata.json
ipyext-0.1.0.dist-info/top_level.txt
