Metadata-Version: 2.0
Name: ipyext
Version: 0.1.0
Summary: IPython-extensions: more magic(s) for IPython
Home-page: https://github.com/ipython-contrib/IPython-extensions
Author: IPython-extensions Development Team
Author-email: jupyter@googlegroups.org
License: BSD
Platform: UNKNOWN
Requires-Dist: ipython
